ABM.cpython-37m-darwin.so
ABMpy-2.0.1.dist-info/METADATA
ABMpy-2.0.1.dist-info/WHEEL
ABMpy-2.0.1.dist-info/top_level.txt
ABMpy-2.0.1.dist-info/RECORD
