Metadata-Version: 2.1
Name: ABMpy
Version: 2.0.1
Summary: Agent-based modeling framework
Home-page: UNKNOWN
Author: Jalil Nourisa
Author-email: jalil.nourisa@gmail.com
License: UNKNOWN
Download-URL: https://github.com/janursa/ABM
Platform: UNKNOWN
